matiCalpackage/__init__.py
matiCalpackage/add.py
matiCalpackage/subtract.py
matiCalpackage/extras/__init__.py
matiCalpackage/extras/divide.py
matiCalpackage/extras/multiply.py
FirstPackageMvilleg1-0.0.1.dist-info/METADATA
FirstPackageMvilleg1-0.0.1.dist-info/WHEEL
FirstPackageMvilleg1-0.0.1.dist-info/top_level.txt
FirstPackageMvilleg1-0.0.1.dist-info/RECORD
